{
    "Employee": [
        {
            "id":"Employee 1",
            "Name":"Juan Pérez",
            "Age":35,
            "Position":"Senior Developer",
            "Department":"Technology",
            "Salary":75000,
            "Location":"Madrid, Spain"
        },
        {
            "id":"Employee 2",
            "Name":"María Rodríguez ",
            "Age":28,
            "Position":"Graphic Designer ",
            "Department":"Design ",
            "Salary":60000,
            "Location":"Paris, France "
        },
        {
            "id":"Employee 3",
            "Name":"Carlos Gómez  ",
            "Age":40,
            "Position":"Project Manager  ",
            "Department":"Project Management  ",
            "Salary":90000,
            "Location":"Berlín, Germany "
        }
    ]
}